pymeshfix/meshfix.py
pymeshfix/_meshfix.cp310-win_amd64.pyd
pymeshfix/_version.py
pymeshfix/__init__.py
pymeshfix/examples/fix.py
pymeshfix/examples/planar_mesh.ply
pymeshfix/examples/StanfordBunny.ply
pymeshfix/examples/__init__.py
pymeshfix-0.17.2.dist-info/DELVEWHEEL
pymeshfix-0.17.2.dist-info/METADATA
pymeshfix-0.17.2.dist-info/RECORD
pymeshfix-0.17.2.dist-info/top_level.txt
pymeshfix-0.17.2.dist-info/WHEEL
pymeshfix-0.17.2.dist-info/licenses/LICENSE
pymeshfix.libs/msvcp140-a4c2229bdc2a2a630acdc095b4d86008.dll
