Metadata-Version: 2.4
Name: pymeshfix
Version: 0.17.2
Summary: Repair triangular meshes using MeshFix
Home-page: https://github.com/pyvista/pymeshfix
Author: PyVista Developers
Author-email: info@pyvista.org
License: GPLv3
Keywords: meshfix
Classifier: Development Status :: 4 - Beta
Classifier: Intended Audience :: Science/Research
Classifier: License :: OSI Approved :: GNU General Public License v3 (GPLv3)
Classifier: Programming Language :: Python :: 3.9
Classifier: Programming Language :: Python :: 3.10
Classifier: Programming Language :: Python :: 3.11
Classifier: Programming Language :: Python :: 3.12
Classifier: Programming Language :: Python :: 3.13
Classifier: Programming Language :: Python :: 3.14
Requires-Python: >=3.9
License-File: LICENSE
Requires-Dist: numpy>1.11.0
Requires-Dist: pyvista>=0.30.0
Dynamic: author
Dynamic: author-email
Dynamic: classifier
Dynamic: description
Dynamic: description-content-type
Dynamic: home-page
Dynamic: keywords
Dynamic: license
Dynamic: license-file
Dynamic: requires-dist
Dynamic: requires-python
Dynamic: summary
